bvPlayer/VideoPlayer.py
bvPlayer/__init__.py
bvPlayer/bvPlayer.py
bvPlayer-0.4.0.dist-info/LICENSE.txt
bvPlayer-0.4.0.dist-info/METADATA
bvPlayer-0.4.0.dist-info/WHEEL
bvPlayer-0.4.0.dist-info/top_level.txt
bvPlayer-0.4.0.dist-info/RECORD
