Metadata-Version: 2.1
Name: bvPlayer
Version: 0.4.0
Summary: A borderless video player with sound
Home-page: https://github.com/jwcarlson01/bvPlayer
Author: Joshua Carlson
Author-email: joshuacarlson@cedarville.edu
License: UNKNOWN
Platform: UNKNOWN
Classifier: Programming Language :: Python :: 3
Classifier: License :: OSI Approved :: MIT License
Classifier: Operating System :: OS Independent
License-File: LICENSE.txt
Requires-Dist: ffpyplayer (>=4.3.2)
Requires-Dist: opencv-python (>=4.5.5.62)
Requires-Dist: Pillow (>=9.0.1)
